colonoscopy-0.1.0.dist-info/METADATA
colonoscopy-0.1.0.dist-info/WHEEL
colonoscopy/__init__.py
colonoscopy/colonoscopy.cpython-312-x86_64-linux-gnu.so
colonoscopy-0.1.0.dist-info/RECORD
